igwn_archive/__init__.py
igwn_archive/source.py
igwn_archive-0.1.1.dist-info/LICENSE
igwn_archive-0.1.1.dist-info/METADATA
igwn_archive-0.1.1.dist-info/WHEEL
igwn_archive-0.1.1.dist-info/entry_points.txt
igwn_archive-0.1.1.dist-info/top_level.txt
igwn_archive-0.1.1.dist-info/RECORD
