Metadata-Version: 2.1
Name: igwn-archive
Version: 0.1.1
Summary: Utilities for interacting with the IGWN Software Archive
Home-page: https://git.ligo.org/computing/packaging/igwn-archive/
Download-URL: https://git.ligo.org/computing/packaging/igwn-archive/releases/
Author: Duncan Macleod
Author-email: duncan.macleod@ligo.org
License: GPL-3.0-or-later
Project-URL: Bug Tracker, https://git.ligo.org/computing/packaging/igwn-archive/issues/
Project-URL: Documentation, https://computing.docs.ligo.org/guide/software/distribution/
Project-URL: Source Code, https://git.ligo.org/computing/packaging/igwn-archive/
Classifier: Development Status :: 4 - Beta
Classifier: Intended Audience :: Science/Research
Classifier: Intended Audience :: End Users/Desktop
Classifier: Intended Audience :: Developers
Classifier: License :: OSI Approved :: GNU General Public License v3 or later (GPLv3+)
Classifier: Natural Language :: English
Classifier: Operating System :: OS Independent
Classifier: Programming Language :: Python
Classifier: Programming Language :: Python :: 3
Classifier: Programming Language :: Python :: 3.6
Classifier: Programming Language :: Python :: 3.7
Classifier: Programming Language :: Python :: 3.8
Classifier: Programming Language :: Python :: 3.9
Classifier: Programming Language :: Python :: 3.10
Classifier: Programming Language :: Python :: 3.11
Classifier: Programming Language :: Python :: 3.12
Classifier: Topic :: Scientific/Engineering
Classifier: Topic :: Scientific/Engineering :: Astronomy
Classifier: Topic :: Scientific/Engineering :: Physics
Requires-Python: >=3.6
License-File: LICENSE
